edds_process/__init__.py
edds_process/globals.py
edds_process/request/__init__.py
edds_process/response/__init__.py
edds_process/response/make.py
edds_process/response/parse.py
edds_process-0.10.0.dist-info/LICENSE
edds_process-0.10.0.dist-info/METADATA
edds_process-0.10.0.dist-info/WHEEL
edds_process-0.10.0.dist-info/RECORD
